odoo/addons/pos_open_cashbox_after_payment/README.rst
odoo/addons/pos_open_cashbox_after_payment/__init__.py
odoo/addons/pos_open_cashbox_after_payment/__manifest__.py
odoo/addons/pos_open_cashbox_after_payment/i18n/it.po
odoo/addons/pos_open_cashbox_after_payment/i18n/pos_open_cashbox_after_payment.pot
odoo/addons/pos_open_cashbox_after_payment/readme/CONTRIBUTORS.md
odoo/addons/pos_open_cashbox_after_payment/readme/DESCRIPTION.md
odoo/addons/pos_open_cashbox_after_payment/static/description/icon.png
odoo/addons/pos_open_cashbox_after_payment/static/description/index.html
odoo/addons/pos_open_cashbox_after_payment/static/src/js/payment_screen.esm.js
odoo_addon_pos_open_cashbox_after_payment-17.0.1.0.0.3.dist-info/METADATA
odoo_addon_pos_open_cashbox_after_payment-17.0.1.0.0.3.dist-info/WHEEL
odoo_addon_pos_open_cashbox_after_payment-17.0.1.0.0.3.dist-info/top_level.txt
odoo_addon_pos_open_cashbox_after_payment-17.0.1.0.0.3.dist-info/RECORD
